sqlauth/__init__.py
sqlauth/cli.py
sqlauth/set_credentials.py
sqlauth/sqlauth.py
sqlauthandle-0.1.0.dist-info/AUTHORS.rst
sqlauthandle-0.1.0.dist-info/LICENSE
sqlauthandle-0.1.0.dist-info/METADATA
sqlauthandle-0.1.0.dist-info/WHEEL
sqlauthandle-0.1.0.dist-info/entry_points.txt
sqlauthandle-0.1.0.dist-info/top_level.txt
sqlauthandle-0.1.0.dist-info/RECORD
