Metadata-Version: 2.1
Name: sqlauthandle
Version: 0.1.0
Summary: Python Boilerplate contains all the boilerplate you need to create a Python package.
Home-page: https://github.com/mentoldo/sqlauth
Author: Matías Adrián Alfonso
Author-email: matias.alfonso@gmail.com
License: MIT license
Keywords: sqlauth
Platform: UNKNOWN
Classifier: Development Status :: 2 - Pre-Alpha
Classifier: Intended Audience :: Developers
Classifier: License :: OSI Approved :: MIT License
Classifier: Natural Language :: English
Classifier: Programming Language :: Python :: 3
Classifier: Programming Language :: Python :: 3.6
Classifier: Programming Language :: Python :: 3.7
Classifier: Programming Language :: Python :: 3.8
Requires-Python: >=3.6
License-File: LICENSE
License-File: AUTHORS.rst
Requires-Dist: Click (>=7.0)
Requires-Dist: sqlalchemy
Requires-Dist: configparser
Requires-Dist: keyring
Requires-Dist: Path
Requires-Dist: tk
Requires-Dist: getpass
